fake_store/URLs.py
fake_store/__init__.py
fake_store/fake_store.py
fake_store_api_wrapper_jopgood-0.3.dist-info/LICENSE
fake_store_api_wrapper_jopgood-0.3.dist-info/METADATA
fake_store_api_wrapper_jopgood-0.3.dist-info/WHEEL
fake_store_api_wrapper_jopgood-0.3.dist-info/top_level.txt
fake_store_api_wrapper_jopgood-0.3.dist-info/RECORD
