Metadata-Version: 2.1
Name: fake_store_api_wrapper_jopgood
Version: 0.3
Summary: A small API wrapper for the Fake Store API.
Author-email: James Hopgood <jehopgood@gmail.com>
Project-URL: Homepage, https://github.com/Jopgood/Fake-Store-API-Wrapper
Project-URL: Issues, https://github.com/Jopgood/Fake-Store-API-Wrapper/issues
Classifier: Development Status :: 5 - Production/Stable
Classifier: Environment :: Console
Classifier: Intended Audience :: End Users/Desktop
Classifier: Natural Language :: English
Classifier: Operating System :: OS Independent
Classifier: Programming Language :: Python
Classifier: Topic :: Internet :: WWW/HTTP :: Dynamic Content :: CGI Tools/Libraries
Classifier: Topic :: Utilities
Classifier: License :: OSI Approved :: MIT License
Requires-Python: >=3.11
License-File: LICENSE
